music_datagen/__init__.py
music_datagen/data_functions.py
music_datagen/datagen.py
music_datagen-0.0.2.dist-info/LICENSE
music_datagen-0.0.2.dist-info/METADATA
music_datagen-0.0.2.dist-info/WHEEL
music_datagen-0.0.2.dist-info/top_level.txt
music_datagen-0.0.2.dist-info/RECORD
